django_markdown_messaging/__init__.py
django_markdown_messaging/admin.py
django_markdown_messaging/apps.py
django_markdown_messaging/migrations/0001_initial.py
django_markdown_messaging/migrations/__init__.py
django_markdown_messaging/models.py
django_markdown_messaging/templates/messaging/base.html
django_markdown_messaging/templates/messaging/edit-message.html
django_markdown_messaging/templates/messaging/index.html
django_markdown_messaging/templates/messaging/message.html
django_markdown_messaging/tests.py
django_markdown_messaging/urls.py
django_markdown_messaging/views.py
django_markdown_messaging-0.1.0.dist-info/LICENSE
django_markdown_messaging-0.1.0.dist-info/WHEEL
django_markdown_messaging-0.1.0.dist-info/METADATA
django_markdown_messaging-0.1.0.dist-info/RECORD
