Metadata-Version: 2.1
Name: django-markdown-messaging
Version: 0.1.0
Summary: Django application to create messages based on markdown
Home-page: https://gitlab.com/aloha68/django-markdown-messaging
License: ISC
Author: Aloha68
Author-email: dev@aloha.im
Requires-Python: >=3.5,<4.0
Classifier: Environment :: Web Environment
Classifier: Framework :: Django
Classifier: Framework :: Django :: 2.2
Classifier: License :: OSI Approved
Classifier: Operating System :: OS Independent
Classifier: Programming Language :: Python :: 3
Classifier: Programming Language :: Python :: 3.5
Classifier: Programming Language :: Python :: 3.6
Classifier: Programming Language :: Python :: 3.7
Classifier: Topic :: Communications
Requires-Dist: django (>=2.2,<3.0)
Requires-Dist: markdown (>=2.6,<3.0)
Project-URL: Repository, https://gitlab.com/aloha68/django-markdown-messaging
